mongoodm/__init__.py
tests/__init__.py
tests/document_test.py
mongoodm-0.0.13.dist-info/LICENCE
mongoodm-0.0.13.dist-info/METADATA
mongoodm-0.0.13.dist-info/WHEEL
mongoodm-0.0.13.dist-info/top_level.txt
mongoodm-0.0.13.dist-info/RECORD
